{
    "中国将始终是世界发展的重要机遇": [
        {
            "time": "2023-10-31 00:15:22.761552+08:00",
            "hot_index": "4918176"
        },
        {
            "time": "2023-10-31 01:10:31.436721+08:00",
            "hot_index": "4971525"
        },
        {
            "time": "2023-10-31 02:15:21.917748+08:00",
            "hot_index": "4915057"
        },
        {
            "time": "2023-10-31 03:09:22.480631+08:00",
            "hot_index": "4984479"
        }
    ],
    "菲舰非法闯入黄岩岛海域 解放军回应": [
        {
            "time": "2023-10-31 00:15:22.761552+08:00",
            "hot_index": "4965183"
        },
        {
            "time": "2023-10-31 01:10:31.436721+08:00",
            "hot_index": "4926443"
        },
        {
            "time": "2023-10-31 02:15:21.917748+08:00",
            "hot_index": "4979624"
        },
        {
            "time": "2023-10-31 03:09:22.480631+08:00",
            "hot_index": "4957724"
        }
    ],
    "夸克被罚款50万": [
        {
            "time": "2023-10-31 00:15:22.761552+08:00",
            "hot_index": "4852809"
        },
        {
            "time": "2023-10-31 01:10:31.436721+08:00",
            "hot_index": "4870958"
        },
        {
            "time": "2023-10-31 02:15:21.917748+08:00",
            "hot_index": "4821583"
        },
        {
            "time": "2023-10-31 03:09:22.480631+08:00",
            "hot_index": "4849183"
        }
    ],
    "建设航天强国是我们的航天梦": [
        {
            "time": "2023-10-31 00:15:22.761552+08:00",
            "hot_index": "4738738"
        },
        {
            "time": "2023-10-31 01:10:31.436721+08:00",
            "hot_index": "4783874"
        },
        {
            "time": "2023-10-31 02:15:21.917748+08:00",
            "hot_index": "4739068"
        },
        {
            "time": "2023-10-31 03:09:22.480631+08:00",
            "hot_index": "4774375"
        }
    ],
    "央媒：“鼻吸能量棒”该管管了！": [
        {
            "time": "2023-10-31 00:15:22.761552+08:00",
            "hot_index": "4662683"
        },
        {
            "time": "2023-10-31 01:10:31.436721+08:00",
            "hot_index": "4634604"
        },
        {
            "time": "2023-10-31 02:15:21.917748+08:00",
            "hot_index": "4699686"
        },
        {
            "time": "2023-10-31 03:09:22.480631+08:00",
            "hot_index": "4652651"
        }
    ],
    "被哈马斯绑架的德以双国籍女子已死": [
        {
            "time": "2023-10-31 00:15:22.761552+08:00",
            "hot_index": "4571907"
        },
        {
            "time": "2023-10-31 01:10:31.436721+08:00",
            "hot_index": "4524559"
        },
        {
            "time": "2023-10-31 02:15:21.917748+08:00",
            "hot_index": "4106734"
        },
        {
            "time": "2023-10-31 03:09:22.480631+08:00",
            "hot_index": "3981472"
        }
    ],
    "恒大歌舞团团长：遭谣言攻击 已报案": [
        {
            "time": "2023-10-31 00:15:22.761552+08:00",
            "hot_index": "4411790"
        },
        {
            "time": "2023-10-31 01:10:31.436721+08:00",
            "hot_index": "3420689"
        },
        {
            "time": "2023-10-31 02:15:21.917748+08:00",
            "hot_index": "3644531"
        },
        {
            "time": "2023-10-31 03:09:22.480631+08:00",
            "hot_index": "4406259"
        }
    ],
    "租客在厕所吊顶发现10万金器": [
        {
            "time": "2023-10-31 00:15:22.761552+08:00",
            "hot_index": "4312598"
        },
        {
            "time": "2023-10-31 03:09:22.480631+08:00",
            "hot_index": "2955883"
        }
    ],
    "“保健石”可放心佩戴？": [
        {
            "time": "2023-10-31 00:15:22.761552+08:00",
            "hot_index": "4269649"
        },
        {
            "time": "2023-10-31 01:10:31.436721+08:00",
            "hot_index": "4294063"
        },
        {
            "time": "2023-10-31 02:15:21.917748+08:00",
            "hot_index": "4272468"
        },
        {
            "time": "2023-10-31 03:09:22.480631+08:00",
            "hot_index": "4213921"
        }
    ],
    "9月全国销售彩票527.74亿": [
        {
            "time": "2023-10-31 00:15:22.761552+08:00",
            "hot_index": "4127792"
        }
    ],
    "航天员将为中国空间站拍全貌照": [
        {
            "time": "2023-10-31 00:15:22.761552+08:00",
            "hot_index": "4001163"
        }
    ],
    "官方调查学生屁股被老师打成黑紫色": [
        {
            "time": "2023-10-31 00:15:22.761552+08:00",
            "hot_index": "3986842"
        }
    ],
    "张雪峰回应公司明年2月只上7天班": [
        {
            "time": "2023-10-31 00:15:22.761552+08:00",
            "hot_index": "3806187"
        },
        {
            "time": "2023-10-31 01:10:31.436721+08:00",
            "hot_index": "3805619"
        }
    ],
    "研究表明金星早期或能孕育生命": [
        {
            "time": "2023-10-31 00:15:22.761552+08:00",
            "hot_index": "3771204"
        },
        {
            "time": "2023-10-31 01:10:31.436721+08:00",
            "hot_index": "3375353"
        },
        {
            "time": "2023-10-31 02:15:21.917748+08:00",
            "hot_index": "3455387"
        },
        {
            "time": "2023-10-31 03:09:22.480631+08:00",
            "hot_index": "3681898"
        }
    ],
    "苹果官方首次宣告iPhone 15系列降价": [
        {
            "time": "2023-10-31 00:15:22.761552+08:00",
            "hot_index": "3697607"
        },
        {
            "time": "2023-10-31 01:10:31.436721+08:00",
            "hot_index": "3765221"
        },
        {
            "time": "2023-10-31 02:15:21.917748+08:00",
            "hot_index": "3316195"
        },
        {
            "time": "2023-10-31 03:09:22.480631+08:00",
            "hot_index": "3720400"
        }
    ],
    "17岁高中生颈椎后凸堪比47岁": [
        {
            "time": "2023-10-31 00:15:22.761552+08:00",
            "hot_index": "3530712"
        },
        {
            "time": "2023-10-31 01:10:31.436721+08:00",
            "hot_index": "3298229"
        },
        {
            "time": "2023-10-31 02:15:21.917748+08:00",
            "hot_index": "2002803"
        },
        {
            "time": "2023-10-31 03:09:22.480631+08:00",
            "hot_index": "2552123"
        }
    ],
    "叙利亚境内美军基地遭炮击爆炸": [
        {
            "time": "2023-10-31 00:15:22.761552+08:00",
            "hot_index": "3429198"
        }
    ],
    "今年已有6省份“一把手”调整": [
        {
            "time": "2023-10-31 00:15:22.761552+08:00",
            "hot_index": "3304171"
        }
    ],
    "世界500强企业正威集团生死局": [
        {
            "time": "2023-10-31 00:15:22.761552+08:00",
            "hot_index": "3277277"
        }
    ],
    "巴总统：巴以冲突或成全球冲突": [
        {
            "time": "2023-10-31 00:15:22.761552+08:00",
            "hot_index": "3160930"
        },
        {
            "time": "2023-10-31 01:10:31.436721+08:00",
            "hot_index": "3626451"
        },
        {
            "time": "2023-10-31 02:15:21.917748+08:00",
            "hot_index": "2545326"
        },
        {
            "time": "2023-10-31 03:09:22.480631+08:00",
            "hot_index": "2850495"
        }
    ],
    "辽宁省畜牧兽医局4人被决定逮捕": [
        {
            "time": "2023-10-31 00:15:22.761552+08:00",
            "hot_index": "3084834"
        },
        {
            "time": "2023-10-31 03:09:22.480631+08:00",
            "hot_index": "2315583"
        }
    ],
    "全职妈妈跳楼 丈夫发现其遭电诈": [
        {
            "time": "2023-10-31 00:15:22.761552+08:00",
            "hot_index": "2989190"
        }
    ],
    "云南边境3所学校因缅甸战事停课": [
        {
            "time": "2023-10-31 00:15:22.761552+08:00",
            "hot_index": "2828143"
        },
        {
            "time": "2023-10-31 01:10:31.436721+08:00",
            "hot_index": "2882183"
        },
        {
            "time": "2023-10-31 03:09:22.480631+08:00",
            "hot_index": "2232566"
        }
    ],
    "金价突破620每克": [
        {
            "time": "2023-10-31 00:15:22.761552+08:00",
            "hot_index": "2727660"
        },
        {
            "time": "2023-10-31 01:10:31.436721+08:00",
            "hot_index": "3500837"
        },
        {
            "time": "2023-10-31 02:15:21.917748+08:00",
            "hot_index": "2920193"
        },
        {
            "time": "2023-10-31 03:09:22.480631+08:00",
            "hot_index": "3442407"
        }
    ],
    "以色列每天损失上亿美元": [
        {
            "time": "2023-10-31 00:15:22.761552+08:00",
            "hot_index": "2652468"
        },
        {
            "time": "2023-10-31 01:10:31.436721+08:00",
            "hot_index": "2229570"
        },
        {
            "time": "2023-10-31 02:15:21.917748+08:00",
            "hot_index": "3887410"
        },
        {
            "time": "2023-10-31 03:09:22.480631+08:00",
            "hot_index": "3598774"
        }
    ],
    "女毒贩为逃避刑罚6年生4娃": [
        {
            "time": "2023-10-31 00:15:22.761552+08:00",
            "hot_index": "2503235"
        },
        {
            "time": "2023-10-31 01:10:31.436721+08:00",
            "hot_index": "3173825"
        },
        {
            "time": "2023-10-31 02:15:21.917748+08:00",
            "hot_index": "3012096"
        },
        {
            "time": "2023-10-31 03:09:22.480631+08:00",
            "hot_index": "3293979"
        }
    ],
    "养老公寓爆雷 686名老人起诉被驳回": [
        {
            "time": "2023-10-31 00:15:22.761552+08:00",
            "hot_index": "2487850"
        }
    ],
    "网友吃席发现每人面前都是盒饭": [
        {
            "time": "2023-10-31 00:15:22.761552+08:00",
            "hot_index": "2363334"
        }
    ],
    "男子炫耀市中心养烈性犬被行拘": [
        {
            "time": "2023-10-31 00:15:22.761552+08:00",
            "hot_index": "2279471"
        },
        {
            "time": "2023-10-31 01:10:31.436721+08:00",
            "hot_index": "2615312"
        },
        {
            "time": "2023-10-31 02:15:21.917748+08:00",
            "hot_index": "3233769"
        }
    ],
    "自闭症儿童地铁吃东西遭老人谩骂": [
        {
            "time": "2023-10-31 00:15:22.761552+08:00",
            "hot_index": "2177366"
        }
    ],
    "7人把别墅样板间偷成毛坯房": [
        {
            "time": "2023-10-31 00:15:22.761552+08:00",
            "hot_index": "2055092"
        },
        {
            "time": "2023-10-31 01:10:31.436721+08:00",
            "hot_index": "2770273"
        },
        {
            "time": "2023-10-31 02:15:21.917748+08:00",
            "hot_index": "2306844"
        },
        {
            "time": "2023-10-31 03:09:22.480631+08:00",
            "hot_index": "2731059"
        }
    ],
    "丰田汽车会长再“炮轰”电动汽车": [
        {
            "time": "2023-10-31 01:10:31.436721+08:00",
            "hot_index": "4486039"
        },
        {
            "time": "2023-10-31 02:15:21.917748+08:00",
            "hot_index": "4530952"
        }
    ],
    "以军发布进攻加沙画面": [
        {
            "time": "2023-10-31 01:10:31.436721+08:00",
            "hot_index": "4307771"
        }
    ],
    "奥运冠军陈若琳拟进京任职": [
        {
            "time": "2023-10-31 01:10:31.436721+08:00",
            "hot_index": "4160368"
        }
    ],
    "曝华为小米选择力挺国产CMOS厂商": [
        {
            "time": "2023-10-31 01:10:31.436721+08:00",
            "hot_index": "4081842"
        },
        {
            "time": "2023-10-31 02:15:21.917748+08:00",
            "hot_index": "4351925"
        }
    ],
    "中央军委副主席张又侠谈台湾问题": [
        {
            "time": "2023-10-31 01:10:31.436721+08:00",
            "hot_index": "3971320"
        }
    ],
    "男子偷菜游戏上瘾多次盗窃蔬菜": [
        {
            "time": "2023-10-31 01:10:31.436721+08:00",
            "hot_index": "3025995"
        }
    ],
    "女子花270订酒店套房竟有会议室": [
        {
            "time": "2023-10-31 01:10:31.436721+08:00",
            "hot_index": "2945709"
        }
    ],
    "郭敬明发新戏男主原图被骂": [
        {
            "time": "2023-10-31 01:10:31.436721+08:00",
            "hot_index": "2527774"
        },
        {
            "time": "2023-10-31 02:15:21.917748+08:00",
            "hot_index": "2848396"
        }
    ],
    "小杨哥和徒弟定期直播未开播": [
        {
            "time": "2023-10-31 01:10:31.436721+08:00",
            "hot_index": "2445190"
        },
        {
            "time": "2023-10-31 02:15:21.917748+08:00",
            "hot_index": "3152827"
        },
        {
            "time": "2023-10-31 03:09:22.480631+08:00",
            "hot_index": "3331141"
        }
    ],
    "电影版花千骨定档": [
        {
            "time": "2023-10-31 01:10:31.436721+08:00",
            "hot_index": "2311824"
        },
        {
            "time": "2023-10-31 02:15:21.917748+08:00",
            "hot_index": "2665024"
        }
    ],
    "大妈健身拉断石栏杆 官方：用力不当": [
        {
            "time": "2023-10-31 01:10:31.436721+08:00",
            "hot_index": "2119763"
        },
        {
            "time": "2023-10-31 03:09:22.480631+08:00",
            "hot_index": "3008881"
        }
    ],
    "中国科学院院士演示隐身术": [
        {
            "time": "2023-10-31 01:10:31.436721+08:00",
            "hot_index": "2052781"
        }
    ],
    "加沙民众回应哄抢联合国救援仓库": [
        {
            "time": "2023-10-31 02:15:21.917748+08:00",
            "hot_index": "4435935"
        }
    ],
    "华为申请“遥遥领先”商标": [
        {
            "time": "2023-10-31 02:15:21.917748+08:00",
            "hot_index": "4029776"
        }
    ],
    "万圣节cos甄嬛滑冰骑车醉酒": [
        {
            "time": "2023-10-31 02:15:21.917748+08:00",
            "hot_index": "3931725"
        }
    ],
    "52岁环卫大姐自考大学3年已过6门": [
        {
            "time": "2023-10-31 02:15:21.917748+08:00",
            "hot_index": "3717504"
        }
    ],
    "中美近期密集接触释放何种信号": [
        {
            "time": "2023-10-31 02:15:21.917748+08:00",
            "hot_index": "3513968"
        }
    ],
    "候鸟可以飞多远？高科技手段揭秘": [
        {
            "time": "2023-10-31 02:15:21.917748+08:00",
            "hot_index": "2758190"
        }
    ],
    "第一批90后已成为中风高发人群": [
        {
            "time": "2023-10-31 02:15:21.917748+08:00",
            "hot_index": "2498781"
        }
    ],
    "18岁男生为买摩托车半价卖房": [
        {
            "time": "2023-10-31 02:15:21.917748+08:00",
            "hot_index": "2216491"
        },
        {
            "time": "2023-10-31 03:09:22.480631+08:00",
            "hot_index": "3183021"
        }
    ],
    "苹果官方iPhone以旧换新价格暴涨": [
        {
            "time": "2023-10-31 02:15:21.917748+08:00",
            "hot_index": "2180535"
        }
    ],
    "网友裸辞炒股5个月亏损48%": [
        {
            "time": "2023-10-31 03:09:22.480631+08:00",
            "hot_index": "4561611"
        }
    ],
    "中使馆回应G7呼吁撤销对日进口限制": [
        {
            "time": "2023-10-31 03:09:22.480631+08:00",
            "hot_index": "4318813"
        }
    ],
    "朱立伦：一定会做到让台湾安全": [
        {
            "time": "2023-10-31 03:09:22.480631+08:00",
            "hot_index": "4117889"
        }
    ],
    "TST庭秘密何以“脱罪”": [
        {
            "time": "2023-10-31 03:09:22.480631+08:00",
            "hot_index": "4040871"
        }
    ],
    "乌克兰将不再允许俄天然气过境": [
        {
            "time": "2023-10-31 03:09:22.480631+08:00",
            "hot_index": "3844204"
        }
    ],
    "约旦要求美国在其境内部署爱国者": [
        {
            "time": "2023-10-31 03:09:22.480631+08:00",
            "hot_index": "2630185"
        }
    ],
    "俄罗斯一机场爆发反犹太骚乱": [
        {
            "time": "2023-10-31 03:09:22.480631+08:00",
            "hot_index": "2458088"
        }
    ],
    "媒体:小杨哥们低俗带货赢流量输底线": [
        {
            "time": "2023-10-31 03:09:22.480631+08:00",
            "hot_index": "2184858"
        }
    ],
    "功夫巨星孟海出殡 洪金宝送别": [
        {
            "time": "2023-10-31 03:09:22.480631+08:00",
            "hot_index": "2075202"
        }
    ]
}